[
  {
    "id": "阿爾アル",
    "name": "阿爾アル",
    "group": "1年E班導 / 輔助理論教師",
    "tags": []
  },
  {
    "id": "阿強",
    "name": "阿強",
    "group": "一年B班助教",
    "tags": [
      "(內含黑色流星請注意)"
    ]
  },
  {
    "id": "妮可泥",
    "name": "妮可泥",
    "group": "一年B班班導 / 美術史老師",
    "tags": [
      "兼代課老師"
    ]
  },
  {
    "id": "迦羅",
    "name": "迦羅",
    "group": "一年C班班導 / 神話學老師",
    "tags": [
      "回家社社團顧問"
    ]
  },
  {
    "id": "帕比咪帕比波",
    "name": "帕比咪帕比波",
    "group": "一年D班班導 / 藝術才藝教師",
    "tags": [
      "提倡愛的教育、小動物友善社及手工社社團顧問"
    ]
  },
  {
    "id": "骰藝",
    "name": "骰藝",
    "group": "一年G班班導 / SAN值檢定老師",
    "tags": [
      "兼任桌遊社社團顧問"
    ]
  },
  {
    "id": "蚩尤",
    "name": "蚩尤",
    "group": "二年A班班導 / 手工藝課老師",
    "tags": [
      "兼任超自然研究社顧問"
    ]
  },
  {
    "id": "黃品奕",
    "name": "黃品奕",
    "group": "二年B班班導 / 國文課老師",
    "tags": [
      "兼任公關部社團顧問"
    ]
  },
  {
    "id": "歐飯",
    "name": "歐飯",
    "group": "二年C班班導 / 幻獸學老師",
    "tags": []
  },
  {
    "id": "早日",
    "name": "早日",
    "group": "二年E班班導 / 遊戲介面教師",
    "tags": [
      "兼任平面設計、嘴pya專門"
    ]
  },
  {
    "id": "塔努努",
    "name": "塔努努",
    "group": "三年A班班導 / 生物課老師",
    "tags": [
      "桌遊社、小動物天體營、校報社、廣播社、WSS社社團顧問"
    ]
  },
  {
    "id": "喵柚 MaoYu",
    "name": "喵柚 MaoYu",
    "group": "三年B班班導 / Live2D操偶老師",
    "tags": [
      "麻將麻雀部 社團顧問"
    ]
  },
  {
    "id": "貓祭",
    "name": "貓祭",
    "group": "三年C班班導 / 投資理財老師",
    "tags": [
      "企業經營顧問"
    ]
  },
  {
    "id": "仰夜星辰",
    "name": "仰夜星辰",
    "group": "三年D班班導 / 生物老師",
    "tags": [
      "睡劇研究社任課老師"
    ]
  },
  {
    "id": "安吉爾",
    "name": "安吉爾",
    "group": "三年F班班導 / 生物課老師",
    "tags": []
  },
  {
    "id": "悠璐",
    "name": "悠璐",
    "group": "請繪製完成後再選位 / 色彩學老師",
    "tags": [
      "（繪製中 待補）"
    ]
  },
  {
    "id": "海鮮生",
    "name": "海鮮生",
    "group": "代理教師 / 數學課老師",
    "tags": [
      "學務處生輔組組長"
    ]
  },
  {
    "id": "Aoi Hinamori",
    "name": "Aoi Hinamori",
    "group": "代課老師 / 保健室老師",
    "tags": []
  },
  {
    "id": "喵君",
    "name": "喵君",
    "group": "代課老師",
    "tags": [
      "HARDCORE社顧問"
    ]
  },
  {
    "id": "抖抖",
    "name": "抖抖",
    "group": "代課老師 / 經濟學老師",
    "tags": [
      "半路被一隻狐狸敲頭 醒來就在這"
    ]
  },
  {
    "id": "米悠栗",
    "name": "米悠栗",
    "group": "外聘老師 / 保健室老師",
    "tags": []
  },
  {
    "id": "南部 書之助",
    "name": "南部 書之助",
    "group": "外聘老師 / 說書表演課程老師",
    "tags": [
      "超自然研究社代理顧問"
    ]
  },
  {
    "id": "鬼塚 真嗣",
    "name": "鬼塚 真嗣",
    "group": "外聘教師 / 攝影課導師",
    "tags": []
  },
  {
    "id": "夏娜奇",
    "name": "夏娜奇",
    "group": "外聘顧問",
    "tags": [
      "貓行為諮商師 兼躲貓貓社老師"
    ]
  },
  {
    "id": "瘋狂的香蕉",
    "name": "瘋狂的香蕉",
    "group": "合作社阿姨",
    "tags": []
  },
  {
    "id": "陳火舌",
    "name": "陳火舌",
    "group": "科任老師 / 台語課老師",
    "tags": []
  },
  {
    "id": "吳喬寧",
    "name": "吳喬寧",
    "group": "科任老師 / 文化史老師",
    "tags": [
      "兼駐校作家、熱音社顧問"
    ]
  },
  {
    "id": "巫喵王肉球",
    "name": "巫喵王肉球",
    "group": "科任老師 / 家政課老師",
    "tags": [
      "小動物天體營副社團顧問"
    ]
  },
  {
    "id": "水無月悠歌",
    "name": "水無月悠歌",
    "group": "科任老師 / 遊戲設計概論老師",
    "tags": []
  },
  {
    "id": "弟宗",
    "name": "弟宗",
    "group": "科任老師 / 國文課老師",
    "tags": [
      "兼任熱舞社社團顧問"
    ]
  },
  {
    "id": "漆瀨奕",
    "name": "漆瀨奕",
    "group": "科任老師 / 粵語課老師",
    "tags": []
  },
  {
    "id": "理真",
    "name": "理真",
    "group": "科任老師 / 調酒課老師",
    "tags": []
  },
  {
    "id": "匕刀",
    "name": "匕刀",
    "group": "科任老師 / 美術老師",
    "tags": []
  },
  {
    "id": "白川赤子",
    "name": "白川赤子",
    "group": "科任老師 / 體育老師",
    "tags": [
      "零食社、柔道社、游泳社老師"
    ]
  },
  {
    "id": "一駝羊",
    "name": "一駝羊",
    "group": "科任老師 / 園藝老師",
    "tags": [
      "園藝社老師"
    ]
  },
  {
    "id": "柊",
    "name": "柊",
    "group": "科任老師 / 木系精靈學老師",
    "tags": [
      "偶爾出沒園藝社"
    ]
  },
  {
    "id": "凌封玄",
    "name": "凌封玄",
    "group": "科任老師 / 地球科學老師",
    "tags": [
      "兼任素養課老師"
    ]
  },
  {
    "id": "安瑟倫．洛朗",
    "name": "安瑟倫．洛朗",
    "group": "科任老師 / 歷史科老師",
    "tags": []
  },
  {
    "id": "沃布姬稻",
    "name": "沃布姬稻",
    "group": "科任老師 / 音樂科老師",
    "tags": [
      "兼管樂社指揮老師"
    ]
  },
  {
    "id": "梁君王",
    "name": "梁君王",
    "group": "科任老師 / 多媒體老師",
    "tags": [
      "網絡工程顧問"
    ]
  },
  {
    "id": "須羽",
    "name": "須羽",
    "group": "科任老師 / 音樂科老師",
    "tags": []
  },
  {
    "id": "狗三歲",
    "name": "狗三歲",
    "group": "科任老師 / 體育課老師",
    "tags": []
  },
  {
    "id": "老布",
    "name": "老布",
    "group": "科任老師 / 異世界歷史老師",
    "tags": [
      "上課愛講一堆有的沒的"
    ]
  },
  {
    "id": "螢",
    "name": "螢",
    "group": "科任老師 / 妖術老師",
    "tags": []
  },
  {
    "id": "鶴目瑞羽",
    "name": "鶴目瑞羽",
    "group": "科任老師 / 綜合課老師",
    "tags": [
      "歡迎隨時來借課，不然我教案不夠用"
    ]
  },
  {
    "id": "塔芭絲可",
    "name": "塔芭絲可",
    "group": "科任老師 / 健康教育老師",
    "tags": []
  },
  {
    "id": "藍妹摁系密魯",
    "name": "藍妹摁系密魯",
    "group": "科任老師 / 手工藝老師",
    "tags": []
  },
  {
    "id": "江腦鷥",
    "name": "江腦鷥",
    "group": "科任老師 / 美術老師",
    "tags": [
      "會在池塘邊盯著持裡面的魚"
    ]
  },
  {
    "id": "玄武",
    "name": "玄武",
    "group": "食堂廚師",
    "tags": []
  },
  {
    "id": "八雲劍",
    "name": "八雲劍",
    "group": "科任老師 / 家政科",
    "tags": [
      "可兼任清潔工，除靈什麼的"
    ]
  },
  {
    "id": "裂雷（詛咒狀態）",
    "name": "裂雷（詛咒狀態）",
    "group": "校園主廚 / 代課烹飪老師",
    "tags": [
      "夜間經營個人酒吧"
    ]
  },
  {
    "id": "怒辣",
    "name": "怒辣",
    "group": "校園怪談 / 小精靈",
    "tags": [
      "學校的神秘小幫手"
    ]
  },
  {
    "id": "方小紅",
    "name": "方小紅",
    "group": "校醫 / 心理輔導員",
    "tags": []
  },
  {
    "id": "馬卡龍",
    "name": "馬卡龍",
    "group": "專任老師 / 保健室老師",
    "tags": []
  },
  {
    "id": "王神羽",
    "name": "王神羽",
    "group": "專任教師 / 社會科老師",
    "tags": [
      "教務處課務組長"
    ]
  },
  {
    "id": "夏爾蓋",
    "name": "夏爾蓋",
    "group": "專任教師 / 輔導老師",
    "tags": []
  },
  {
    "id": "夏艾爾",
    "name": "夏艾爾",
    "group": "專任教師 / 生物老師",
    "tags": [
      "教古生物學，體型太大進不去教室或辦公室"
    ]
  },
  {
    "id": "黃依儒",
    "name": "黃依儒",
    "group": "教官",
    "tags": []
  },
  {
    "id": "赤斯特",
    "name": "赤斯特",
    "group": "教官 / 資訊科老師",
    "tags": []
  },
  {
    "id": "簡拾參",
    "name": "簡拾參",
    "group": "教官 / 調酒證照培訓師",
    "tags": []
  },
  {
    "id": "緹緹帕拉斯",
    "name": "緹緹帕拉斯",
    "group": "通識講師 / 惡魔史/黑魔法",
    "tags": [
      "可借課，也可代課"
    ]
  },
  {
    "id": "里沃斯",
    "name": "里沃斯",
    "group": "圖書館館員 / 代班老師",
    "tags": []
  },
  {
    "id": "黒澤ユイ",
    "name": "黒澤ユイ",
    "group": "實習老師 / 設計概論老師",
    "tags": [
      "夢境特工部社團顧問"
    ]
  },
  {
    "id": "千羽織雪",
    "name": "千羽織雪",
    "group": "實習老師 / 冰雪魔法系老師",
    "tags": [
      "睡覺研究社顧問"
    ]
  },
  {
    "id": "夏海鮮",
    "name": "夏海鮮",
    "group": "福利社阿姨",
    "tags": []
  },
  {
    "id": "K阿爾伯特",
    "name": "K阿爾伯特",
    "group": "輔導主任 / 人類觀察學教授",
    "tags": [
      "動漫研究社顧問"
    ]
  },
  {
    "id": "白岳臣",
    "name": "白岳臣",
    "group": "學校保全",
    "tags": []
  },
  {
    "id": "蘇雪霏",
    "name": "蘇雪霏",
    "group": "學校餐廳阿姨",
    "tags": [
      "秘密經營冰店"
    ]
  },
  {
    "id": "斯洛姆",
    "name": "斯洛姆",
    "group": "總務主任 / 地球科學課老師",
    "tags": [
      "地理課老師"
    ]
  },
  {
    "id": "零夜",
    "name": "零夜",
    "group": "警衛",
    "tags": []
  },
  {
    "id": "赤野蕗丹",
    "name": "赤野蕗丹",
    "group": "體育老師",
    "tags": []
  },
  {
    "id": "醜狗培培",
    "name": "醜狗培培",
    "group": "教職員",
    "tags": [
      "失智的前教務主任"
    ]
  },
  {
    "id": "蘇墨",
    "name": "蘇墨",
    "group": "輔導老師",
    "tags": []
  },
  {
    "id": "老宅男蒼大叔",
    "name": "老宅男蒼大叔",
    "group": "福利社麵點師",
    "tags": [
      "中式麵點研究社顧問"
    ]
  },
  {
    "id": "桃米",
    "name": "桃米",
    "group": "科任老師 / 藝術課老師",
    "tags": []
  },
  {
    "id": "夏澪Karin",
    "name": "夏澪Karin",
    "group": "外聘教師",
    "tags": [
      "畫不完社教師"
    ]
  },
  {
    "id": "娜娜",
    "name": "娜娜",
    "group": "科任老師 / 英文課老師",
    "tags": [
      "下班後會去駐唱"
    ]
  },
  {
    "id": "咪呀",
    "name": "咪呀",
    "group": "總務處庶務組 / 處理雜事",
    "tags": [
      "水電修繕人員"
    ]
  },
  {
    "id": "佐間ぺん",
    "name": "佐間ぺん",
    "group": "外聘教師 / 冥想課老師",
    "tags": [
      "學校好多好吃的東西 ペンペン當老師"
    ]
  },
  {
    "id": "小六",
    "name": "小六",
    "group": "教學助理TA / 神話學助教",
    "tags": [
      "精靈學助教"
    ]
  },
  {
    "id": "剝離",
    "name": "剝離",
    "group": "輔導員",
    "tags": []
  },
  {
    "id": "維塔",
    "name": "維塔",
    "group": "外聘教師",
    "tags": [
      "觸手研究社教師"
    ]
  },
  {
    "id": "Ms.瓦倫汀",
    "name": "Ms.瓦倫汀",
    "group": "秘書 / 翻譯官",
    "tags": []
  },
  {
    "id": "夢魅戴菈",
    "name": "夢魅戴菈",
    "group": "科任老師 / 英文老師",
    "tags": [
      "兼任日文老師"
    ]
  },
  {
    "id": "菈媞耶阿芭芭",
    "name": "菈媞耶阿芭芭",
    "group": "科任老師 / 魔王學概論老師",
    "tags": [
      "龍種學科老師"
    ]
  },
  {
    "id": "4-2(神崎 烈)",
    "name": "4-2(神崎 烈)",
    "group": "外聘老師 / 表演藝術老師",
    "tags": [
      "音樂劇專門學科"
    ]
  },
  {
    "id": "溫檸檬",
    "name": "溫檸檬",
    "group": "外聘老師 / 選修課-V聲繪影",
    "tags": [
      "來修學分旁聽拿獎盃"
    ]
  },
  {
    "id": "巫菈妮亞",
    "name": "巫菈妮亞",
    "group": "代理體育老師 / 真實身分是魔女",
    "tags": [
      "教課的目的是來物色年輕小弟弟（？"
    ]
  },
  {
    "id": "魚子楊桃",
    "name": "魚子楊桃",
    "group": "外聘老師 / 美術、自習課老師",
    "tags": [
      "發想各種有趣的繪畫活動"
    ]
  },
  {
    "id": "雲貓",
    "name": "雲貓",
    "group": "二年G班班導 / 時空生存學老師",
    "tags": [
      "被動技能:無法控制且隨機的被時空轉移"
    ]
  },
  {
    "id": "傑克．艾莉索(餅",
    "name": "傑克．艾莉索(餅",
    "group": "科任老師 / 體育老師、安全講師",
    "tags": [
      "體育課強度極高，但卻是最擔心學生安全的"
    ]
  },
  {
    "id": "秋之楓空",
    "name": "秋之楓空",
    "group": "科任老師 / 自然藥草學老師",
    "tags": [
      "很常突然上課一半消失"
    ]
  },
  {
    "id": "歐歐涅",
    "name": "歐歐涅",
    "group": "科任老師 / 魔草學老師",
    "tags": [
      "培養植物系魔物，目標是統治校園花圃美化校園"
    ]
  },
  {
    "id": "周参見 英雄",
    "name": "周参見 英雄",
    "group": "3年E班班導師 / 刑事警察科",
    "tags": []
  },
  {
    "id": "伊芙琳・羅希爾",
    "name": "伊芙琳・羅希爾",
    "group": "科任老師 / 國文老師",
    "tags": [
      "常駐教具報廢區，歡迎找老師聊天"
    ]
  },
  {
    "id": "雲景夏",
    "name": "雲景夏",
    "group": "一年F班班導 / “普通”的代課老師",
    "tags": [
      "有時在零號O壩 有時在蓮華O城 有時在瓦爾O拉斯"
    ]
  },
  {
    "id": "澄",
    "name": "澄",
    "group": "科任老師 / 美術老師",
    "tags": []
  },
  {
    "id": "回收姬",
    "name": "回收姬",
    "group": "垃圾處理員",
    "tags": [
      "晚上會趁沒人的時候把垃圾收走"
    ]
  },
  {
    "id": "諾比六花",
    "name": "諾比六花",
    "group": "外聘教師 / 色彩調配與材料工藝專任講師",
    "tags": [
      "百鬼夜行社顧問  色彩調配老師"
    ]
  },
  {
    "id": "黃幽丕",
    "name": "黃幽丕",
    "group": "社團&任課老師 / 昆蟲學",
    "tags": [
      "兼任節肢動物社師"
    ]
  },
  {
    "id": "嵐加",
    "name": "嵐加",
    "group": "校犬(狼)",
    "tags": [
      "看似在巡邏實則是在找舒服的地方趴著休息"
    ]
  },
  {
    "id": "小泉 赤",
    "name": "小泉 赤",
    "group": "科任老師 / 食療科老師",
    "tags": [
      "常常會帶小甜點請學生吃"
    ]
  },
  {
    "id": "藍昕晨",
    "name": "藍昕晨",
    "group": "學校餐廳工作人員",
    "tags": []
  },
  {
    "id": "Meko",
    "name": "Meko",
    "group": "清潔阿伯",
    "tags": [
      "跟三年D班的辣咩醬是兄妹"
    ]
  },
  {
    "id": "邱品瑞",
    "name": "邱品瑞",
    "group": "科任老師 / 歷史科老師",
    "tags": [
      "兼任熱音社、綜合格鬥社顧問"
    ]
  },
  {
    "id": "伊匹毆",
    "name": "伊匹毆",
    "group": "地下書庫圖書管理員",
    "tags": [
      "會沒收你不該帶來學校的書籍"
    ]
  },
  {
    "id": "迪鹿(月鹿)",
    "name": "迪鹿(月鹿)",
    "group": "校醫 / 保健室巫醫",
    "tags": [
      "治療方式是祈禱與讓學生起乩"
    ]
  },
  {
    "id": "伊竇華",
    "name": "伊竇華",
    "group": "科任老師 / 英文科/選修課日文",
    "tags": [
      "兼任台語代課教師"
    ]
  },
  {
    "id": "名取德蘭",
    "name": "名取德蘭",
    "group": "科任老師 / 虛無與存在概論",
    "tags": [
      "兼任咒與祈願概念"
    ]
  },
  {
    "id": "亭",
    "name": "亭",
    "group": "科任老師 / 美術助教",
    "tags": [
      "兼任圖書館助理"
    ]
  },
  {
    "id": "貓貓卡愛",
    "name": "貓貓卡愛",
    "group": "圖書館資訊組織分析師",
    "tags": [
      "我相信世間萬物都有屬於自己的索書號"
    ]
  },
  {
    "id": "擔擔麵",
    "name": "擔擔麵",
    "group": "專任教師 / 輔導老師",
    "tags": [
      "麻將社(台麻)社團顧問"
    ]
  },
  {
    "id": "麥可",
    "name": "麥可",
    "group": "總務主任 / 活動中心管理員",
    "tags": [
      "2A阿毛的遠房表叔"
    ]
  },
  {
    "id": "戴琉璃",
    "name": "戴琉璃",
    "group": "科任老師 / 地理科老師",
    "tags": [
      "哆啦D夢、總務處庶務組行政職"
    ]
  },
  {
    "id": "新川 椿十郎",
    "name": "新川 椿十郎",
    "group": "社團&科任老師 / 外文系老師",
    "tags": [
      "弓道社顧問老師"
    ]
  },
  {
    "id": "律",
    "name": "律",
    "group": "設計相關科系專任老師 / 设计系(群)",
    "tags": []
  },
  {
    "id": "瓏蒼瓊璦",
    "name": "瓏蒼瓊璦",
    "group": "校車司機 / 校車司機",
    "tags": []
  },
  {
    "id": "葉阿諾",
    "name": "葉阿諾",
    "group": "動物教育實習老師 / 寵物、動物教育",
    "tags": []
  },
  {
    "id": "海文德•D•加斯塔",
    "name": "海文德•D•加斯塔",
    "group": "文化史與象徵研究客座教師 / 圖書館館藏追回員",
    "tags": [
      "文化史與象徵研究客座教師"
    ]
  },
  {
    "id": "奇姆斯坦",
    "name": "奇姆斯坦",
    "group": "工友",
    "tags": []
  },
  {
    "id": "雪鴞殊與",
    "name": "雪鴞殊與",
    "group": "郵務長",
    "tags": []
  },
  {
    "id": "基利斯",
    "name": "基利斯",
    "group": "多媒體設計科系老師 / 手工藝社團老師",
    "tags": [
      "三年G班級班導"
    ]
  },
  {
    "id": "多內爾",
    "name": "多內爾",
    "group": "生物老師 / 生物老師",
    "tags": []
  },
  {
    "id": "墨水月",
    "name": "墨水月",
    "group": "奇物學約聘教師兼圖書館值班人員 / 奇物學教師兼圖書館值班人員",
    "tags": []
  },
  {
    "id": "哈比特",
    "name": "哈比特",
    "group": "食堂區的點心房主廚",
    "tags": []
  },
  {
    "id": "裕日望",
    "name": "裕日望",
    "group": "體育老師 / 體育老師",
    "tags": []
  },
  {
    "id": "裏明",
    "name": "裏明",
    "group": "繪畫助教 / 繪畫助教",
    "tags": []
  },
  {
    "id": "楷",
    "name": "楷",
    "group": "外聘助教",
    "tags": [
      "兼任3D建模研究社顧問"
    ]
  },
  {
    "id": "沫藍",
    "name": "沫藍",
    "group": "二年D班班導 / 英文教師",
    "tags": []
  },
  {
    "id": "蝦咪",
    "name": "蝦咪",
    "group": "校貓",
    "tags": [
      "在學校裡賣萌蹭吃蹭喝"
    ]
  },
  {
    "id": "影川",
    "name": "影川",
    "group": "掃地工",
    "tags": []
  },
  {
    "id": "米希卡",
    "name": "米希卡",
    "group": "醫務室 / 心理補導師",
    "tags": []
  }
]